pysmo/__init__.py
pysmo/aimbat/__init__.py
pysmo/aimbat/algiccs.py
pysmo/aimbat/algmccc.py
pysmo/aimbat/filtering.py
pysmo/aimbat/pickphase.py
pysmo/aimbat/plotphase.py
pysmo/aimbat/plotstations.py
pysmo/aimbat/plotutils.py
pysmo/aimbat/prepdata.py
pysmo/aimbat/prepplot.py
pysmo/aimbat/qualctrl.py
pysmo/aimbat/qualsort.py
pysmo/aimbat/sacpickle.py
pysmo/aimbat/stationmapping.py
pysmo/aimbat/ttconfig.py
pysmo/aimbat/ttdefaults.conf
pysmo/aimbat/ttguiqt.py
pysmo/aimbat/xcorr.py
pysmo/aimbat/xcorrf90.cpython-37m-darwin.so
pysmo.aimbat-1.0.5.dist-info/METADATA
pysmo.aimbat-1.0.5.dist-info/WHEEL
pysmo.aimbat-1.0.5.dist-info/entry_points.txt
pysmo.aimbat-1.0.5.dist-info/top_level.txt
pysmo.aimbat-1.0.5.dist-info/RECORD
