Metadata-Version: 2.1
Name: pysmo.aimbat
Version: 1.0.5
Summary: UNKNOWN
Home-page: http://www.earth.northwestern.edu/~xlou/aimbat.html
Author: Xiaoting Lou
Author-email: xlou@u.northwestern.edu
License: GNU General Public License, Version 3 (GPLv3)
Platform: Mac OS X
Platform: Linux/Unix
Platform: Windows
Requires-Dist: scipy
Requires-Dist: numpy
Requires-Dist: matplotlib
Requires-Dist: pyqtgraph
Requires-Dist: pysmo
